<element>
  <elementId>115</elementId>
  <glyphs>
    <variantMap>
      <entry>
        <int>1</int>
        <glyph>
          <centrePoint>0</centrePoint>
          <height>100</height>
          <pGlyphVariant>
            <int>2</int>
            <int>1</int>
            <int>0</int>
            <int>0</int>
          </pGlyphVariant>
          <pHeight>
            <int>100</int>
            <int>96</int>
            <int>0</int>
            <int>0</int>
          </pHeight>
          <pWidth>
            <int>100</int>
            <int>50</int>
            <int>0</int>
            <int>0</int>
          </pWidth>
          <pX>
            <int>0</int>
            <int>48</int>
            <int>0</int>
            <int>0</int>
          </pX>
          <pY>
            <int>0</int>
            <int>4</int>
            <int>0</int>
            <int>0</int>
          </pY>
          <standalone>false</standalone>
          <strokeCount>16</strokeCount>
          <strokes>
            <strokes/>
          </strokes>
          <width>100</width>
        </glyph>
      </entry>
    </variantMap>
  </glyphs>
  <pElementId>
    <int>1730</int>
    <int>1869</int>
    <int>0</int>
    <int>0</int>
  </pElementId>
  <pattern>H2</pattern>
</element>