<element>
  <elementId>1996</elementId>
  <pattern>V2</pattern>
  <pElementId>
    <int>639</int>
    <int>1910</int>
    <int>0</int>
    <int>0</int>
  </pElementId>
  <glyphs>
    <variantMap>
      <entry>
        <int>1</int>
        <glyph>
          <width>100</width>
          <height>100</height>
          <pGlyphVariant>
            <int>1</int>
            <int>1</int>
            <int>0</int>
            <int>0</int>
          </pGlyphVariant>
          <pX>
            <int>0</int>
            <int>0</int>
            <int>0</int>
            <int>0</int>
          </pX>
          <pY>
            <int>0</int>
            <int>45</int>
            <int>0</int>
            <int>0</int>
          </pY>
          <pWidth>
            <int>100</int>
            <int>100</int>
            <int>0</int>
            <int>0</int>
          </pWidth>
          <pHeight>
            <int>50</int>
            <int>55</int>
            <int>0</int>
            <int>0</int>
          </pHeight>
          <strokes>
            <strokes>
              <stroke>
                <segments>
                  <segment>
                    <type>M</type>
                    <points>
                      <float>23.82102</float>
                      <float>6.385335</float>
                      <float>0.0</float>
                      <float>0.0</float>
                      <float>0.0</float>
                      <float>0.0</float>
                    </points>
                  </segment>
                  <segment>
                    <type>C</type>
                    <points>
                      <float>22.23682</float>
                      <float>15.304599</float>
                      <float>19.07432</float>
                      <float>22.721287</float>
                      <float>13.69762</float>
                      <float>27.506311</float>
                    </points>
                  </segment>
                </segments>
              </stroke>
              <stroke>
                <segments>
                  <segment>
                    <type>M</type>
                    <points>
                      <float>21.69809</float>
                      <float>13.83652</float>
                      <float>0.0</float>
                      <float>0.0</float>
                      <float>0.0</float>
                      <float>0.0</float>
                    </points>
                  </segment>
                  <segment>
                    <type>L</type>
                    <points>
                      <float>82.38989</float>
                      <float>13.83652</float>
                      <float>0.0</float>
                      <float>0.0</float>
                      <float>0.0</float>
                      <float>0.0</float>
                    </points>
                  </segment>
                </segments>
              </stroke>
              <stroke>
                <segments>
                  <segment>
                    <type>M</type>
                    <points>
                      <float>6.91824</float>
                      <float>32.3899</float>
                      <float>0.0</float>
                      <float>0.0</float>
                      <float>0.0</float>
                      <float>0.0</float>
                    </points>
                  </segment>
                  <segment>
                    <type>L</type>
                    <points>
                      <float>91.8239</float>
                      <float>32.3899</float>
                      <float>0.0</float>
                      <float>0.0</float>
                      <float>0.0</float>
                      <float>0.0</float>
                    </points>
                  </segment>
                </segments>
              </stroke>
              <stroke>
                <segments>
                  <segment>
                    <type>M</type>
                    <points>
                      <float>40.487762</float>
                      <float>13.593146</float>
                      <float>0.0</float>
                      <float>0.0</float>
                      <float>0.0</float>
                      <float>0.0</float>
                    </points>
                  </segment>
                  <segment>
                    <type>C</type>
                    <points>
                      <float>37.33116</float>
                      <float>34.070683</float>
                      <float>22.218962</float>
                      <float>50.140804</float>
                      <float>7.093842</float>
                      <float>62.04098</float>
                    </points>
                  </segment>
                </segments>
              </stroke>
              <stroke>
                <segments>
                  <segment>
                    <type>M</type>
                    <points>
                      <float>22.543276</float>
                      <float>48.593586</float>
                      <float>0.0</float>
                      <float>0.0</float>
                      <float>0.0</float>
                      <float>0.0</float>
                    </points>
                  </segment>
                  <segment>
                    <type>L</type>
                    <points>
                      <float>22.5</float>
                      <float>93.88889</float>
                      <float>0.0</float>
                      <float>0.0</float>
                      <float>0.0</float>
                      <float>0.0</float>
                    </points>
                  </segment>
                </segments>
              </stroke>
              <stroke>
                <segments>
                  <segment>
                    <type>M</type>
                    <points>
                      <float>60.215843</float>
                      <float>36.65558</float>
                      <float>0.0</float>
                      <float>0.0</float>
                      <float>0.0</float>
                      <float>0.0</float>
                    </points>
                  </segment>
                  <segment>
                    <type>C</type>
                    <points>
                      <float>58.392925</float>
                      <float>40.634956</float>
                      <float>56.266254</float>
                      <float>44.816624</float>
                      <float>52.012913</float>
                      <float>48.39138</float>
                    </points>
                  </segment>
                </segments>
              </stroke>
              <stroke>
                <segments>
                  <segment>
                    <type>M</type>
                    <points>
                      <float>22.543276</float>
                      <float>48.3913</float>
                      <float>0.0</float>
                      <float>0.0</float>
                      <float>0.0</float>
                      <float>0.0</float>
                    </points>
                  </segment>
                  <segment>
                    <type>L</type>
                    <points>
                      <float>88.16642</float>
                      <float>48.3913</float>
                      <float>0.0</float>
                      <float>0.0</float>
                      <float>0.0</float>
                      <float>0.0</float>
                    </points>
                  </segment>
                </segments>
              </stroke>
              <stroke>
                <segments>
                  <segment>
                    <type>M</type>
                    <points>
                      <float>52.620525</float>
                      <float>48.39128</float>
                      <float>0.0</float>
                      <float>0.0</float>
                      <float>0.0</float>
                      <float>0.0</float>
                    </points>
                  </segment>
                  <segment>
                    <type>L</type>
                    <points>
                      <float>52.500004</float>
                      <float>89.72223</float>
                      <float>0.0</float>
                      <float>0.0</float>
                      <float>0.0</float>
                      <float>0.0</float>
                    </points>
                  </segment>
                </segments>
              </stroke>
              <stroke>
                <segments>
                  <segment>
                    <type>M</type>
                    <points>
                      <float>23.150976</float>
                      <float>63.162155</float>
                      <float>0.0</float>
                      <float>0.0</float>
                      <float>0.0</float>
                      <float>0.0</float>
                    </points>
                  </segment>
                  <segment>
                    <type>L</type>
                    <points>
                      <float>82.69777</float>
                      <float>63.162155</float>
                      <float>0.0</float>
                      <float>0.0</float>
                      <float>0.0</float>
                      <float>0.0</float>
                    </points>
                  </segment>
                </segments>
              </stroke>
              <stroke>
                <segments>
                  <segment>
                    <type>M</type>
                    <points>
                      <float>23.454737</float>
                      <float>78.13529</float>
                      <float>0.0</float>
                      <float>0.0</float>
                      <float>0.0</float>
                      <float>0.0</float>
                    </points>
                  </segment>
                  <segment>
                    <type>L</type>
                    <points>
                      <float>82.69777</float>
                      <float>78.13529</float>
                      <float>0.0</float>
                      <float>0.0</float>
                      <float>0.0</float>
                      <float>0.0</float>
                    </points>
                  </segment>
                </segments>
              </stroke>
              <stroke>
                <segments>
                  <segment>
                    <type>M</type>
                    <points>
                      <float>22.5</float>
                      <float>90.27779</float>
                      <float>0.0</float>
                      <float>0.0</float>
                      <float>0.0</float>
                      <float>0.0</float>
                    </points>
                  </segment>
                  <segment>
                    <type>L</type>
                    <points>
                      <float>87.77779</float>
                      <float>90.27779</float>
                      <float>0.0</float>
                      <float>0.0</float>
                      <float>0.0</float>
                      <float>0.0</float>
                    </points>
                  </segment>
                </segments>
              </stroke>
            </strokes>
          </strokes>
          <strokeCount>11</strokeCount>
          <centrePoint>0</centrePoint>
          <standalone>true</standalone>
        </glyph>
      </entry>
    </variantMap>
  </glyphs>
</element>