<element>
  <elementId>2168</elementId>
  <pattern>Elt</pattern>
  <pElementId>
    <int>1181</int>
    <int>1672</int>
    <int>0</int>
    <int>0</int>
  </pElementId>
  <glyphs>
    <variantMap>
      <entry>
        <int>1</int>
        <glyph>
          <width>100</width>
          <height>100</height>
          <pGlyphVariant>
            <int>3</int>
            <int>1</int>
            <int>0</int>
            <int>0</int>
          </pGlyphVariant>
          <pX>
            <int>4</int>
            <int>12</int>
            <int>0</int>
            <int>0</int>
          </pX>
          <pY>
            <int>0</int>
            <int>25</int>
            <int>0</int>
            <int>0</int>
          </pY>
          <pWidth>
            <int>91</int>
            <int>88</int>
            <int>0</int>
            <int>0</int>
          </pWidth>
          <pHeight>
            <int>100</int>
            <int>72</int>
            <int>0</int>
            <int>0</int>
          </pHeight>
          <strokes>
            <strokes/>
          </strokes>
          <strokeCount>8</strokeCount>
          <centrePoint>0</centrePoint>
          <standalone>false</standalone>
        </glyph>
      </entry>
    </variantMap>
  </glyphs>
</element>