<element>
  <elementId>2733</elementId>
  <pattern>C</pattern>
  <pElementId>
    <int>911</int>
    <int>0</int>
    <int>0</int>
    <int>0</int>
  </pElementId>
  <glyphs>
    <variantMap>
      <entry>
        <int>1</int>
        <glyph>
          <width>100</width>
          <height>100</height>
          <pGlyphVariant>
            <int>0</int>
            <int>0</int>
            <int>0</int>
            <int>0</int>
          </pGlyphVariant>
          <pX>
            <int>0</int>
            <int>0</int>
            <int>0</int>
            <int>0</int>
          </pX>
          <pY>
            <int>0</int>
            <int>0</int>
            <int>0</int>
            <int>0</int>
          </pY>
          <pWidth>
            <int>0</int>
            <int>0</int>
            <int>0</int>
            <int>0</int>
          </pWidth>
          <pHeight>
            <int>0</int>
            <int>0</int>
            <int>0</int>
            <int>0</int>
          </pHeight>
          <strokes>
            <strokes>
              <stroke>
                <segments>
                  <segment>
                    <type>M</type>
                    <points>
                      <float>12.5786</float>
                      <float>8.80503</float>
                      <float>0.0</float>
                      <float>0.0</float>
                      <float>0.0</float>
                      <float>0.0</float>
                    </points>
                  </segment>
                  <segment>
                    <type>L</type>
                    <points>
                      <float>69.4969</float>
                      <float>8.80503</float>
                      <float>0.0</float>
                      <float>0.0</float>
                      <float>0.0</float>
                      <float>0.0</float>
                    </points>
                  </segment>
                  <segment>
                    <type>L</type>
                    <points>
                      <float>69.4969</float>
                      <float>42.4528</float>
                      <float>0.0</float>
                      <float>0.0</float>
                      <float>0.0</float>
                      <float>0.0</float>
                    </points>
                  </segment>
                  <segment>
                    <type>L</type>
                    <points>
                      <float>92.7673</float>
                      <float>42.4528</float>
                      <float>0.0</float>
                      <float>0.0</float>
                      <float>0.0</float>
                      <float>0.0</float>
                    </points>
                  </segment>
                  <segment>
                    <type>L</type>
                    <points>
                      <float>92.7673</float>
                      <float>69.4968</float>
                      <float>0.0</float>
                      <float>0.0</float>
                      <float>0.0</float>
                      <float>0.0</float>
                    </points>
                  </segment>
                  <segment>
                    <type>C</type>
                    <points>
                      <float>92.9769</float>
                      <float>82.8092</float>
                      <float>86.64864</float>
                      <float>95.0</float>
                      <float>76.918915</float>
                      <float>91.189186</float>
                    </points>
                  </segment>
                  <segment>
                    <type>L</type>
                    <points>
                      <float>70.1081</float>
                      <float>88.27026</float>
                      <float>0.0</float>
                      <float>0.0</float>
                      <float>0.0</float>
                      <float>0.0</float>
                    </points>
                  </segment>
                </segments>
              </stroke>
            </strokes>
          </strokes>
          <strokeCount>1</strokeCount>
          <centrePoint>0</centrePoint>
          <standalone>true</standalone>
        </glyph>
      </entry>
      <entry>
        <int>2</int>
        <glyph>
          <width>100</width>
          <height>100</height>
          <pGlyphVariant>
            <int>0</int>
            <int>0</int>
            <int>0</int>
            <int>0</int>
          </pGlyphVariant>
          <pX>
            <int>0</int>
            <int>0</int>
            <int>0</int>
            <int>0</int>
          </pX>
          <pY>
            <int>0</int>
            <int>0</int>
            <int>0</int>
            <int>0</int>
          </pY>
          <pWidth>
            <int>0</int>
            <int>0</int>
            <int>0</int>
            <int>0</int>
          </pWidth>
          <pHeight>
            <int>0</int>
            <int>0</int>
            <int>0</int>
            <int>0</int>
          </pHeight>
          <strokes>
            <strokes>
              <stroke>
                <segments>
                  <segment>
                    <type>M</type>
                    <points>
                      <float>12.5786</float>
                      <float>8.80503</float>
                      <float>0.0</float>
                      <float>0.0</float>
                      <float>0.0</float>
                      <float>0.0</float>
                    </points>
                  </segment>
                  <segment>
                    <type>L</type>
                    <points>
                      <float>69.4969</float>
                      <float>8.80503</float>
                      <float>0.0</float>
                      <float>0.0</float>
                      <float>0.0</float>
                      <float>0.0</float>
                    </points>
                  </segment>
                  <segment>
                    <type>L</type>
                    <points>
                      <float>69.4969</float>
                      <float>42.4528</float>
                      <float>0.0</float>
                      <float>0.0</float>
                      <float>0.0</float>
                      <float>0.0</float>
                    </points>
                  </segment>
                  <segment>
                    <type>L</type>
                    <points>
                      <float>92.7673</float>
                      <float>42.4528</float>
                      <float>0.0</float>
                      <float>0.0</float>
                      <float>0.0</float>
                      <float>0.0</float>
                    </points>
                  </segment>
                  <segment>
                    <type>L</type>
                    <points>
                      <float>92.7673</float>
                      <float>69.4968</float>
                      <float>0.0</float>
                      <float>0.0</float>
                      <float>0.0</float>
                      <float>0.0</float>
                    </points>
                  </segment>
                  <segment>
                    <type>C</type>
                    <points>
                      <float>92.9769</float>
                      <float>82.8092</float>
                      <float>89.24324</float>
                      <float>91.513504</float>
                      <float>83.4054</float>
                      <float>91.83783</float>
                    </points>
                  </segment>
                  <segment>
                    <type>L</type>
                    <points>
                      <float>81.78378</float>
                      <float>92.162155</float>
                      <float>0.0</float>
                      <float>0.0</float>
                      <float>0.0</float>
                      <float>0.0</float>
                    </points>
                  </segment>
                </segments>
              </stroke>
            </strokes>
          </strokes>
          <strokeCount>1</strokeCount>
          <centrePoint>0</centrePoint>
          <standalone>true</standalone>
        </glyph>
      </entry>
    </variantMap>
  </glyphs>
</element>