<element>
  <elementId>582</elementId>
  <pattern>W</pattern>
  <pElementId>
    <int>0</int>
    <int>0</int>
    <int>0</int>
    <int>0</int>
  </pElementId>
  <glyphs>
    <variantMap>
      <entry>
        <int>1</int>
        <glyph>
          <width>100</width>
          <height>100</height>
          <pGlyphVariant>
            <int>0</int>
            <int>0</int>
            <int>0</int>
            <int>0</int>
          </pGlyphVariant>
          <pX>
            <int>0</int>
            <int>0</int>
            <int>0</int>
            <int>0</int>
          </pX>
          <pY>
            <int>0</int>
            <int>0</int>
            <int>0</int>
            <int>0</int>
          </pY>
          <pWidth>
            <int>0</int>
            <int>0</int>
            <int>0</int>
            <int>0</int>
          </pWidth>
          <pHeight>
            <int>0</int>
            <int>0</int>
            <int>0</int>
            <int>0</int>
          </pHeight>
          <strokes>
            <strokes>
              <stroke>
                <segments>
                  <segment>
                    <type>M</type>
                    <points>
                      <float>19.70297</float>
                      <float>24.329895</float>
                      <float>0.0</float>
                      <float>0.0</float>
                      <float>0.0</float>
                      <float>0.0</float>
                    </points>
                  </segment>
                  <segment>
                    <type>L</type>
                    <points>
                      <float>19.70297</float>
                      <float>47.623764</float>
                      <float>0.0</float>
                      <float>0.0</float>
                      <float>0.0</float>
                      <float>0.0</float>
                    </points>
                  </segment>
                  <segment>
                    <type>C</type>
                    <points>
                      <float>19.70297</float>
                      <float>75.84158</float>
                      <float>16.732674</float>
                      <float>82.07921</float>
                      <float>13.168318</float>
                      <float>88.019806</float>
                    </points>
                  </segment>
                </segments>
              </stroke>
              <stroke>
                <segments>
                  <segment>
                    <type>M</type>
                    <points>
                      <float>19.69072</float>
                      <float>24.455444</float>
                      <float>0.0</float>
                      <float>0.0</float>
                      <float>0.0</float>
                      <float>0.0</float>
                    </points>
                  </segment>
                  <segment>
                    <type>L</type>
                    <points>
                      <float>81.39175</float>
                      <float>24.455444</float>
                      <float>0.0</float>
                      <float>0.0</float>
                      <float>0.0</float>
                      <float>0.0</float>
                    </points>
                  </segment>
                  <segment>
                    <type>L</type>
                    <points>
                      <float>81.39175</float>
                      <float>27.57732</float>
                      <float>0.0</float>
                      <float>0.0</float>
                      <float>0.0</float>
                      <float>0.0</float>
                    </points>
                  </segment>
                  <segment>
                    <type>C</type>
                    <points>
                      <float>81.39175</float>
                      <float>30.206184</float>
                      <float>81.08247</float>
                      <float>32.061855</float>
                      <float>79.69072</float>
                      <float>34.381443</float>
                    </points>
                  </segment>
                </segments>
              </stroke>
              <stroke>
                <segments>
                  <segment>
                    <type>M</type>
                    <points>
                      <float>51.188118</float>
                      <float>9.60396</float>
                      <float>0.0</float>
                      <float>0.0</float>
                      <float>0.0</float>
                      <float>0.0</float>
                    </points>
                  </segment>
                  <segment>
                    <type>L</type>
                    <points>
                      <float>51.188118</float>
                      <float>42.27723</float>
                      <float>0.0</float>
                      <float>0.0</float>
                      <float>0.0</float>
                      <float>0.0</float>
                    </points>
                  </segment>
                </segments>
              </stroke>
              <stroke>
                <segments>
                  <segment>
                    <type>M</type>
                    <points>
                      <float>32.17822</float>
                      <float>42.27723</float>
                      <float>0.0</float>
                      <float>0.0</float>
                      <float>0.0</float>
                      <float>0.0</float>
                    </points>
                  </segment>
                  <segment>
                    <type>L</type>
                    <points>
                      <float>70.49505</float>
                      <float>42.27723</float>
                      <float>0.0</float>
                      <float>0.0</float>
                      <float>0.0</float>
                      <float>0.0</float>
                    </points>
                  </segment>
                  <segment>
                    <type>C</type>
                    <points>
                      <float>66.2986</float>
                      <float>72.0821</float>
                      <float>43.762375</float>
                      <float>88.91089</float>
                      <float>22.376236</float>
                      <float>89.80198</float>
                    </points>
                  </segment>
                </segments>
              </stroke>
              <stroke>
                <segments>
                  <segment>
                    <type>M</type>
                    <points>
                      <float>36.806282</float>
                      <float>43.717278</float>
                      <float>0.0</float>
                      <float>0.0</float>
                      <float>0.0</float>
                      <float>0.0</float>
                    </points>
                  </segment>
                  <segment>
                    <type>C</type>
                    <points>
                      <float>36.828953</float>
                      <float>55.470665</float>
                      <float>62.251305</float>
                      <float>89.58115</float>
                      <float>80.78534</float>
                      <float>89.58115</float>
                    </points>
                  </segment>
                </segments>
              </stroke>
            </strokes>
          </strokes>
          <strokeCount>5</strokeCount>
          <centrePoint>0</centrePoint>
          <standalone>true</standalone>
        </glyph>
      </entry>
      <entry>
        <int>2</int>
        <glyph>
          <width>100</width>
          <height>100</height>
          <pGlyphVariant>
            <int>0</int>
            <int>0</int>
            <int>0</int>
            <int>0</int>
          </pGlyphVariant>
          <pX>
            <int>0</int>
            <int>0</int>
            <int>0</int>
            <int>0</int>
          </pX>
          <pY>
            <int>0</int>
            <int>0</int>
            <int>0</int>
            <int>0</int>
          </pY>
          <pWidth>
            <int>0</int>
            <int>0</int>
            <int>0</int>
            <int>0</int>
          </pWidth>
          <pHeight>
            <int>0</int>
            <int>0</int>
            <int>0</int>
            <int>0</int>
          </pHeight>
          <strokes>
            <strokes>
              <stroke>
                <segments>
                  <segment>
                    <type>M</type>
                    <points>
                      <float>19.70297</float>
                      <float>24.329895</float>
                      <float>0.0</float>
                      <float>0.0</float>
                      <float>0.0</float>
                      <float>0.0</float>
                    </points>
                  </segment>
                  <segment>
                    <type>L</type>
                    <points>
                      <float>19.70297</float>
                      <float>47.623764</float>
                      <float>0.0</float>
                      <float>0.0</float>
                      <float>0.0</float>
                      <float>0.0</float>
                    </points>
                  </segment>
                  <segment>
                    <type>C</type>
                    <points>
                      <float>19.70297</float>
                      <float>75.84158</float>
                      <float>16.732674</float>
                      <float>82.07921</float>
                      <float>13.168318</float>
                      <float>88.019806</float>
                    </points>
                  </segment>
                </segments>
              </stroke>
              <stroke>
                <segments>
                  <segment>
                    <type>M</type>
                    <points>
                      <float>19.69072</float>
                      <float>24.455444</float>
                      <float>0.0</float>
                      <float>0.0</float>
                      <float>0.0</float>
                      <float>0.0</float>
                    </points>
                  </segment>
                  <segment>
                    <type>L</type>
                    <points>
                      <float>81.39175</float>
                      <float>24.455444</float>
                      <float>0.0</float>
                      <float>0.0</float>
                      <float>0.0</float>
                      <float>0.0</float>
                    </points>
                  </segment>
                  <segment>
                    <type>L</type>
                    <points>
                      <float>81.39175</float>
                      <float>27.57732</float>
                      <float>0.0</float>
                      <float>0.0</float>
                      <float>0.0</float>
                      <float>0.0</float>
                    </points>
                  </segment>
                  <segment>
                    <type>C</type>
                    <points>
                      <float>81.39175</float>
                      <float>30.206184</float>
                      <float>81.08247</float>
                      <float>32.061855</float>
                      <float>79.69072</float>
                      <float>34.381443</float>
                    </points>
                  </segment>
                </segments>
              </stroke>
              <stroke>
                <segments>
                  <segment>
                    <type>M</type>
                    <points>
                      <float>51.188118</float>
                      <float>9.60396</float>
                      <float>0.0</float>
                      <float>0.0</float>
                      <float>0.0</float>
                      <float>0.0</float>
                    </points>
                  </segment>
                  <segment>
                    <type>L</type>
                    <points>
                      <float>51.188118</float>
                      <float>42.27723</float>
                      <float>0.0</float>
                      <float>0.0</float>
                      <float>0.0</float>
                      <float>0.0</float>
                    </points>
                  </segment>
                </segments>
              </stroke>
              <stroke>
                <segments>
                  <segment>
                    <type>M</type>
                    <points>
                      <float>26.111115</float>
                      <float>42.222225</float>
                      <float>0.0</float>
                      <float>0.0</float>
                      <float>0.0</float>
                      <float>0.0</float>
                    </points>
                  </segment>
                  <segment>
                    <type>L</type>
                    <points>
                      <float>70.49505</float>
                      <float>42.27723</float>
                      <float>0.0</float>
                      <float>0.0</float>
                      <float>0.0</float>
                      <float>0.0</float>
                    </points>
                  </segment>
                  <segment>
                    <type>C</type>
                    <points>
                      <float>66.2986</float>
                      <float>72.0821</float>
                      <float>43.762375</float>
                      <float>88.91089</float>
                      <float>22.376236</float>
                      <float>89.80198</float>
                    </points>
                  </segment>
                </segments>
              </stroke>
              <stroke>
                <segments>
                  <segment>
                    <type>M</type>
                    <points>
                      <float>30.833336</float>
                      <float>54.72223</float>
                      <float>0.0</float>
                      <float>0.0</float>
                      <float>0.0</float>
                      <float>0.0</float>
                    </points>
                  </segment>
                  <segment>
                    <type>C</type>
                    <points>
                      <float>49.722225</float>
                      <float>58.8889</float>
                      <float>66.94444</float>
                      <float>70.27778</float>
                      <float>78.333336</float>
                      <float>80.833336</float>
                    </points>
                  </segment>
                </segments>
              </stroke>
            </strokes>
          </strokes>
          <strokeCount>5</strokeCount>
          <centrePoint>0</centrePoint>
          <standalone>true</standalone>
        </glyph>
      </entry>
    </variantMap>
  </glyphs>
</element>