<radical>
  <radicalNumber>12</radicalNumber>
  <variants>
    <variantMap>
      <entry>
        <int>2</int>
        <variant>
          <elementId>1983</elementId>
          <mnemonics>
            <DLCMap>
              <entry>
                <string>en</string>
                <mnemonic>
                  <destMnemonic></destMnemonic>
                </mnemonic>
              </entry>
            </DLCMap>
          </mnemonics>
          <names>
            <SLCMap>
              <entry>
                <string>ja</string>
                <radicalName>
                  <sourceName>hachigashira</sourceName>
                </radicalName>
              </entry>
            </SLCMap>
          </names>
          <position>T</position>
          <strokeCount>2</strokeCount>
        </variant>
      </entry>
      <entry>
        <int>4</int>
        <variant>
          <elementId>853</elementId>
          <mnemonics>
            <DLCMap>
              <entry>
                <string>en</string>
                <mnemonic>
                  <destMnemonic></destMnemonic>
                </mnemonic>
              </entry>
            </DLCMap>
          </mnemonics>
          <names>
            <SLCMap>
              <entry>
                <string>ja</string>
                <radicalName>
                  <sourceName>hachi?</sourceName>
                </radicalName>
              </entry>
            </SLCMap>
          </names>
          <position>B</position>
          <strokeCount>2</strokeCount>
        </variant>
      </entry>
      <entry>
        <int>1</int>
        <variant>
          <elementId>1382</elementId>
          <mnemonics>
            <DLCMap>
              <entry>
                <string>en</string>
                <mnemonic>
                  <destMnemonic>Eight</destMnemonic>
                </mnemonic>
              </entry>
            </DLCMap>
          </mnemonics>
          <names>
            <SLCMap>
              <entry>
                <string>ja</string>
                <radicalName>
                  <sourceName>hachi</sourceName>
                </radicalName>
              </entry>
            </SLCMap>
          </names>
          <position>W</position>
          <strokeCount>2</strokeCount>
        </variant>
      </entry>
      <entry>
        <int>3</int>
        <variant>
          <elementId>2481</elementId>
          <mnemonics>
            <DLCMap>
              <entry>
                <string>en</string>
                <mnemonic>
                  <destMnemonic></destMnemonic>
                </mnemonic>
              </entry>
            </DLCMap>
          </mnemonics>
          <names>
            <SLCMap>
              <entry>
                <string>ja</string>
                <radicalName>
                  <sourceName>hachigashira?</sourceName>
                </radicalName>
              </entry>
            </SLCMap>
          </names>
          <position>T</position>
          <strokeCount>2</strokeCount>
        </variant>
      </entry>
    </variantMap>
  </variants>
</radical>