<character>
  <characterId>148</characterId>
  <jaUcsCode>27491</jaUcsCode>
  <jaElementId>1045</jaElementId>
  <jaJisCode>16437</jaJisCode>
  <jaJouyouGrade>1</jaJouyouGrade>
  <zhSimplifiedUcsCode>0</zhSimplifiedUcsCode>
  <zhSimplifiedElementId>0</zhSimplifiedElementId>
  <zhTraditionalUcsCode>0</zhTraditionalUcsCode>
  <zhTraditionalElementId>0</zhTraditionalElementId>
  <readings>
    <SLCMap>
      <entry>
        <string>ja</string>
        <map>
          <entry>
            <int>2</int>
            <reading>
              <sourceReading>ショウ</sourceReading>
              <jpReadingType>on</jpReadingType>
              <meanings>
                <DLCMap>
                  <entry>
                    <string>en</string>
                    <readingMeaning>
                      <destReadingMeaning>correct; justice; straight</destReadingMeaning>
                    </readingMeaning>
                  </entry>
                  <entry>
                    <string>fr</string>
                    <readingMeaning>
                      <destReadingMeaning>correct, justice; droiture</destReadingMeaning>
                    </readingMeaning>
                  </entry>
                </DLCMap>
              </meanings>
            </reading>
          </entry>
          <entry>
            <int>4</int>
            <reading>
              <sourceReading>まさ</sourceReading>
              <jpReadingType>kun</jpReadingType>
              <meanings>
                <DLCMap>
                  <entry>
                    <string>en</string>
                    <readingMeaning>
                      <destReadingMeaning>*</destReadingMeaning>
                    </readingMeaning>
                  </entry>
                  <entry>
                    <string>fr</string>
                    <readingMeaning>
                      <destReadingMeaning>*</destReadingMeaning>
                    </readingMeaning>
                  </entry>
                </DLCMap>
              </meanings>
            </reading>
          </entry>
          <entry>
            <int>6</int>
            <reading>
              <sourceReading>ただ・す</sourceReading>
              <jpReadingType>kun</jpReadingType>
              <meanings>
                <DLCMap>
                  <entry>
                    <string>en</string>
                    <readingMeaning>
                      <destReadingMeaning>to correct, rectify</destReadingMeaning>
                    </readingMeaning>
                  </entry>
                  <entry>
                    <string>fr</string>
                    <readingMeaning>
                      <destReadingMeaning>corriger, rectifier</destReadingMeaning>
                    </readingMeaning>
                  </entry>
                </DLCMap>
              </meanings>
            </reading>
          </entry>
          <entry>
            <int>1</int>
            <reading>
              <sourceReading>セイ</sourceReading>
              <jpReadingType>on</jpReadingType>
              <meanings>
                <DLCMap>
                  <entry>
                    <string>en</string>
                    <readingMeaning>
                      <destReadingMeaning>correct; justice; straight</destReadingMeaning>
                    </readingMeaning>
                  </entry>
                  <entry>
                    <string>fr</string>
                    <readingMeaning>
                      <destReadingMeaning>correct, justice; droiture</destReadingMeaning>
                    </readingMeaning>
                  </entry>
                </DLCMap>
              </meanings>
            </reading>
          </entry>
          <entry>
            <int>3</int>
            <reading>
              <sourceReading>ただ・しい</sourceReading>
              <jpReadingType>kun</jpReadingType>
              <meanings>
                <DLCMap>
                  <entry>
                    <string>en</string>
                    <readingMeaning>
                      <destReadingMeaning>correct, proper</destReadingMeaning>
                    </readingMeaning>
                  </entry>
                  <entry>
                    <string>fr</string>
                    <readingMeaning>
                      <destReadingMeaning>correct, juste</destReadingMeaning>
                    </readingMeaning>
                  </entry>
                </DLCMap>
              </meanings>
            </reading>
          </entry>
          <entry>
            <int>5</int>
            <reading>
              <sourceReading>まさ・に</sourceReading>
              <jpReadingType>kun</jpReadingType>
              <meanings>
                <DLCMap>
                  <entry>
                    <string>en</string>
                    <readingMeaning>
                      <destReadingMeaning>truly, indeed</destReadingMeaning>
                    </readingMeaning>
                  </entry>
                  <entry>
                    <string>fr</string>
                    <readingMeaning>
                      <destReadingMeaning>précisément, en effet</destReadingMeaning>
                    </readingMeaning>
                  </entry>
                </DLCMap>
              </meanings>
            </reading>
          </entry>
        </map>
      </entry>
    </SLCMap>
  </readings>
  <meanings>
    <identifierMap>
      <entry>
        <identifier>
          <sourceLanguageCode>ja</sourceLanguageCode>
          <destLanguageCode>fr</destLanguageCode>
        </identifier>
        <meaning>
          <destMeaning></destMeaning>
        </meaning>
      </entry>
      <entry>
        <identifier>
          <sourceLanguageCode>ja</sourceLanguageCode>
          <destLanguageCode>en</destLanguageCode>
        </identifier>
        <meaning>
          <destMeaning>Correct; Justice</destMeaning>
        </meaning>
      </entry>
    </identifierMap>
  </meanings>
</character>