<character>
  <characterId>193</characterId>
  <jaUcsCode>21368</jaUcsCode>
  <jaElementId>868</jaElementId>
  <jaJisCode>12855</jaJisCode>
  <jaJouyouGrade>7</jaJouyouGrade>
  <zhSimplifiedUcsCode>0</zhSimplifiedUcsCode>
  <zhSimplifiedElementId>0</zhSimplifiedElementId>
  <zhTraditionalUcsCode>0</zhTraditionalUcsCode>
  <zhTraditionalElementId>0</zhTraditionalElementId>
  <readings>
    <SLCMap>
      <entry>
        <string>ja</string>
        <map>
          <entry>
            <int>2</int>
            <reading>
              <sourceReading>おろ・す</sourceReading>
              <jpReadingType>kun</jpReadingType>
              <meanings>
                <DLCMap/>
              </meanings>
            </reading>
          </entry>
          <entry>
            <int>1</int>
            <reading>
              <sourceReading>おろし</sourceReading>
              <jpReadingType>kun</jpReadingType>
              <meanings>
                <DLCMap/>
              </meanings>
            </reading>
          </entry>
        </map>
      </entry>
    </SLCMap>
  </readings>
  <meanings>
    <identifierMap>
      <entry>
        <identifier>
          <sourceLanguageCode>ja</sourceLanguageCode>
          <destLanguageCode>en</destLanguageCode>
        </identifier>
        <meaning>
          <destMeaning>Wholesale</destMeaning>
        </meaning>
      </entry>
    </identifierMap>
  </meanings>
</character>