<character>
  <characterId>2698</characterId>
  <jaUcsCode>31725</jaUcsCode>
  <jaElementId>3373</jaElementId>
  <jaJisCode>20278</jaJisCode>
  <jaJouyouGrade>0</jaJouyouGrade>
  <zhSimplifiedUcsCode>0</zhSimplifiedUcsCode>
  <zhSimplifiedElementId>0</zhSimplifiedElementId>
  <zhTraditionalUcsCode>0</zhTraditionalUcsCode>
  <zhTraditionalElementId>0</zhTraditionalElementId>
  <jaFrequency>0</jaFrequency>
  <readings>
    <SLCMap>
      <entry>
        <string>ja</string>
        <map>
          <entry>
            <int>1</int>
            <reading>
              <sourceReading>ロウ</sourceReading>
              <jpReadingType>on</jpReadingType>
              <meanings>
                <DLCMap>
                  <entry>
                    <string>fr</string>
                    <readingMeaning>
                      <destReadingMeaning></destReadingMeaning>
                    </readingMeaning>
                  </entry>
                  <entry>
                    <string>en</string>
                    <readingMeaning>
                      <destReadingMeaning></destReadingMeaning>
                    </readingMeaning>
                  </entry>
                </DLCMap>
              </meanings>
            </reading>
          </entry>
          <entry>
            <int>2</int>
            <reading>
              <sourceReading>ル</sourceReading>
              <jpReadingType>on</jpReadingType>
              <meanings>
                <DLCMap>
                  <entry>
                    <string>fr</string>
                    <readingMeaning>
                      <destReadingMeaning></destReadingMeaning>
                    </readingMeaning>
                  </entry>
                  <entry>
                    <string>en</string>
                    <readingMeaning>
                      <destReadingMeaning></destReadingMeaning>
                    </readingMeaning>
                  </entry>
                </DLCMap>
              </meanings>
            </reading>
          </entry>
          <entry>
            <int>3</int>
            <reading>
              <sourceReading>かご</sourceReading>
              <jpReadingType>kun</jpReadingType>
              <meanings>
                <DLCMap>
                  <entry>
                    <string>fr</string>
                    <readingMeaning>
                      <destReadingMeaning></destReadingMeaning>
                    </readingMeaning>
                  </entry>
                  <entry>
                    <string>en</string>
                    <readingMeaning>
                      <destReadingMeaning>basket; cage</destReadingMeaning>
                    </readingMeaning>
                  </entry>
                </DLCMap>
              </meanings>
            </reading>
          </entry>
          <entry>
            <int>4</int>
            <reading>
              <sourceReading>こ・める</sourceReading>
              <jpReadingType>kun</jpReadingType>
              <meanings>
                <DLCMap>
                  <entry>
                    <string>fr</string>
                    <readingMeaning>
                      <destReadingMeaning></destReadingMeaning>
                    </readingMeaning>
                  </entry>
                  <entry>
                    <string>en</string>
                    <readingMeaning>
                      <destReadingMeaning></destReadingMeaning>
                    </readingMeaning>
                  </entry>
                </DLCMap>
              </meanings>
            </reading>
          </entry>
          <entry>
            <int>5</int>
            <reading>
              <sourceReading>こも・る</sourceReading>
              <jpReadingType>kun</jpReadingType>
              <meanings>
                <DLCMap>
                  <entry>
                    <string>fr</string>
                    <readingMeaning>
                      <destReadingMeaning></destReadingMeaning>
                    </readingMeaning>
                  </entry>
                  <entry>
                    <string>en</string>
                    <readingMeaning>
                      <destReadingMeaning>to seclude oneself; to be confined in; to be filled (e.g., with emotion); to be heavy (with); to be stuffy; to be implied</destReadingMeaning>
                    </readingMeaning>
                  </entry>
                </DLCMap>
              </meanings>
            </reading>
          </entry>
          <entry>
            <int>6</int>
            <reading>
              <sourceReading>こ・む</sourceReading>
              <jpReadingType>kun</jpReadingType>
              <meanings>
                <DLCMap>
                  <entry>
                    <string>fr</string>
                    <readingMeaning>
                      <destReadingMeaning></destReadingMeaning>
                    </readingMeaning>
                  </entry>
                  <entry>
                    <string>en</string>
                    <readingMeaning>
                      <destReadingMeaning></destReadingMeaning>
                    </readingMeaning>
                  </entry>
                </DLCMap>
              </meanings>
            </reading>
          </entry>
        </map>
      </entry>
    </SLCMap>
  </readings>
  <meanings>
    <identifierMap>
      <entry>
        <identifier>
          <sourceLanguageCode>ja</sourceLanguageCode>
          <destLanguageCode>en</destLanguageCode>
        </identifier>
        <meaning>
          <destMeaning>seclude oneself; cage; coop; implied</destMeaning>
        </meaning>
      </entry>
      <entry>
        <identifier>
          <sourceLanguageCode>ja</sourceLanguageCode>
          <destLanguageCode>fr</destLanguageCode>
        </identifier>
        <meaning>
          <destMeaning></destMeaning>
        </meaning>
      </entry>
    </identifierMap>
  </meanings>
</character>