<character>
  <characterId>3027</characterId>
  <jaUcsCode>28402</jaUcsCode>
  <jaElementId>3721</jaElementId>
  <jaJisCode>24186</jaJisCode>
  <jaJouyouGrade>0</jaJouyouGrade>
  <zhSimplifiedUcsCode>0</zhSimplifiedUcsCode>
  <zhSimplifiedElementId>0</zhSimplifiedElementId>
  <zhTraditionalUcsCode>0</zhTraditionalUcsCode>
  <zhTraditionalElementId>0</zhTraditionalElementId>
  <jaFrequency>0</jaFrequency>
  <readings>
    <SLCMap>
      <entry>
        <string>ja</string>
        <map>
          <entry>
            <int>1</int>
            <reading>
              <sourceReading>シン</sourceReading>
              <jpReadingType>on</jpReadingType>
              <meanings>
                <DLCMap>
                  <entry>
                    <string>fr</string>
                    <readingMeaning>
                      <destReadingMeaning></destReadingMeaning>
                    </readingMeaning>
                  </entry>
                  <entry>
                    <string>en</string>
                    <readingMeaning>
                      <destReadingMeaning></destReadingMeaning>
                    </readingMeaning>
                  </entry>
                </DLCMap>
              </meanings>
            </reading>
          </entry>
          <entry>
            <int>2</int>
            <reading>
              <sourceReading>し・みる</sourceReading>
              <jpReadingType>kun</jpReadingType>
              <meanings>
                <DLCMap>
                  <entry>
                    <string>fr</string>
                    <readingMeaning>
                      <destReadingMeaning></destReadingMeaning>
                    </readingMeaning>
                  </entry>
                  <entry>
                    <string>en</string>
                    <readingMeaning>
                      <destReadingMeaning>to pierce; to penetrate; to soak in; to permeate; to be infected (with vice); to be steeped (with prejudice)</destReadingMeaning>
                    </readingMeaning>
                  </entry>
                </DLCMap>
              </meanings>
            </reading>
          </entry>
          <entry>
            <int>3</int>
            <reading>
              <sourceReading>にじ・む</sourceReading>
              <jpReadingType>kun</jpReadingType>
              <meanings>
                <DLCMap>
                  <entry>
                    <string>fr</string>
                    <readingMeaning>
                      <destReadingMeaning></destReadingMeaning>
                    </readingMeaning>
                  </entry>
                  <entry>
                    <string>en</string>
                    <readingMeaning>
                      <destReadingMeaning>to run; to blur; to spread; to blot; to ooze</destReadingMeaning>
                    </readingMeaning>
                  </entry>
                </DLCMap>
              </meanings>
            </reading>
          </entry>
        </map>
      </entry>
    </SLCMap>
  </readings>
  <meanings>
    <identifierMap>
      <entry>
        <identifier>
          <sourceLanguageCode>ja</sourceLanguageCode>
          <destLanguageCode>en</destLanguageCode>
        </identifier>
        <meaning>
          <destMeaning>imbued with</destMeaning>
        </meaning>
      </entry>
      <entry>
        <identifier>
          <sourceLanguageCode>ja</sourceLanguageCode>
          <destLanguageCode>fr</destLanguageCode>
        </identifier>
        <meaning>
          <destMeaning></destMeaning>
        </meaning>
      </entry>
    </identifierMap>
  </meanings>
</character>