<character>
  <characterId>878</characterId>
  <jaUcsCode>22985</jaUcsCode>
  <jaElementId>1926</jaElementId>
  <jaJisCode>15184</jaJisCode>
  <jaJouyouGrade>2</jaJouyouGrade>
  <zhSimplifiedUcsCode>0</zhSimplifiedUcsCode>
  <zhSimplifiedElementId>0</zhSimplifiedElementId>
  <zhTraditionalUcsCode>0</zhTraditionalUcsCode>
  <zhTraditionalElementId>0</zhTraditionalElementId>
  <readings>
    <SLCMap>
      <entry>
        <string>ja</string>
        <map>
          <entry>
            <int>2</int>
            <reading>
              <sourceReading>あね</sourceReading>
              <jpReadingType>kun</jpReadingType>
              <meanings>
                <DLCMap>
                  <entry>
                    <string>en</string>
                    <readingMeaning>
                      <destReadingMeaning>Older sister</destReadingMeaning>
                    </readingMeaning>
                  </entry>
                  <entry>
                    <string>fr</string>
                    <readingMeaning>
                      <destReadingMeaning>soeur aînée</destReadingMeaning>
                    </readingMeaning>
                  </entry>
                </DLCMap>
              </meanings>
            </reading>
          </entry>
          <entry>
            <int>1</int>
            <reading>
              <sourceReading>シ</sourceReading>
              <jpReadingType>on</jpReadingType>
              <meanings>
                <DLCMap>
                  <entry>
                    <string>en</string>
                    <readingMeaning>
                      <destReadingMeaning>Older sister</destReadingMeaning>
                    </readingMeaning>
                  </entry>
                  <entry>
                    <string>fr</string>
                    <readingMeaning>
                      <destReadingMeaning>soeur aînée</destReadingMeaning>
                    </readingMeaning>
                  </entry>
                </DLCMap>
              </meanings>
            </reading>
          </entry>
          <entry>
            <int>3</int>
            <reading>
              <sourceReading>ねえ</sourceReading>
              <jpReadingType>kun</jpReadingType>
              <meanings>
                <DLCMap>
                  <entry>
                    <string>en</string>
                    <readingMeaning>
                      <destReadingMeaning>Older sister; Miss, young lady</destReadingMeaning>
                    </readingMeaning>
                  </entry>
                  <entry>
                    <string>fr</string>
                    <readingMeaning>
                      <destReadingMeaning>soeur aînée; mademoiselle, demoiselle</destReadingMeaning>
                    </readingMeaning>
                  </entry>
                </DLCMap>
              </meanings>
            </reading>
          </entry>
        </map>
      </entry>
    </SLCMap>
  </readings>
  <meanings>
    <identifierMap>
      <entry>
        <identifier>
          <sourceLanguageCode>ja</sourceLanguageCode>
          <destLanguageCode>en</destLanguageCode>
        </identifier>
        <meaning>
          <destMeaning>Older sister</destMeaning>
        </meaning>
      </entry>
      <entry>
        <identifier>
          <sourceLanguageCode>ja</sourceLanguageCode>
          <destLanguageCode>fr</destLanguageCode>
        </identifier>
        <meaning>
          <destMeaning>Soeur aînée</destMeaning>
        </meaning>
      </entry>
    </identifierMap>
  </meanings>
</character>