<character>
  <characterId>900</characterId>
  <jaUcsCode>35430</jaUcsCode>
  <jaElementId>299</jaElementId>
  <jaJisCode>15214</jaJisCode>
  <jaJouyouGrade>4</jaJouyouGrade>
  <zhSimplifiedUcsCode>0</zhSimplifiedUcsCode>
  <zhSimplifiedElementId>0</zhSimplifiedElementId>
  <zhTraditionalUcsCode>0</zhTraditionalUcsCode>
  <zhTraditionalElementId>0</zhTraditionalElementId>
  <readings>
    <SLCMap>
      <entry>
        <string>ja</string>
        <map>
          <entry>
            <int>2</int>
            <reading>
              <sourceReading>こころ・みる</sourceReading>
              <jpReadingType>kun</jpReadingType>
              <meanings>
                <DLCMap/>
              </meanings>
            </reading>
          </entry>
          <entry>
            <int>1</int>
            <reading>
              <sourceReading>シ</sourceReading>
              <jpReadingType>on</jpReadingType>
              <meanings>
                <DLCMap/>
              </meanings>
            </reading>
          </entry>
          <entry>
            <int>3</int>
            <reading>
              <sourceReading>ため・す</sourceReading>
              <jpReadingType>kun</jpReadingType>
              <meanings>
                <DLCMap/>
              </meanings>
            </reading>
          </entry>
        </map>
      </entry>
    </SLCMap>
  </readings>
  <meanings>
    <identifierMap>
      <entry>
        <identifier>
          <sourceLanguageCode>ja</sourceLanguageCode>
          <destLanguageCode>en</destLanguageCode>
        </identifier>
        <meaning>
          <destMeaning>Test; Try out; Specimen</destMeaning>
        </meaning>
      </entry>
    </identifierMap>
  </meanings>
</character>