<category>
  <categoryId>2</categoryId>
  <names>
    <DLCMap>
      <entry>
        <string>en</string>
        <categoryName>
          <categoryName>Body</categoryName>
        </categoryName>
      </entry>
    </DLCMap>
  </names>
  <members>
    <sequenceMap>
      <entry>
        <int>15</int>
        <member>
          <characterId>377</characterId>
        </member>
      </entry>
      <entry>
        <int>30</int>
        <member>
          <characterId>1482</characterId>
        </member>
      </entry>
      <entry>
        <int>43</int>
        <member>
          <characterId>1791</characterId>
        </member>
      </entry>
      <entry>
        <int>16</int>
        <member>
          <characterId>5</characterId>
        </member>
      </entry>
      <entry>
        <int>31</int>
        <member>
          <characterId>1616</characterId>
        </member>
      </entry>
      <entry>
        <int>48</int>
        <member>
          <characterId>1606</characterId>
        </member>
      </entry>
      <entry>
        <int>32</int>
        <member>
          <characterId>1941</characterId>
        </member>
      </entry>
      <entry>
        <int>34</int>
        <member>
          <characterId>1371</characterId>
        </member>
      </entry>
      <entry>
        <int>41</int>
        <member>
          <characterId>2031</characterId>
        </member>
      </entry>
      <entry>
        <int>96</int>
        <member>
          <characterId>1153</characterId>
        </member>
      </entry>
      <entry>
        <int>97</int>
        <member>
          <characterId>909</characterId>
        </member>
      </entry>
      <entry>
        <int>1</int>
        <member>
          <characterId>395</characterId>
        </member>
      </entry>
      <entry>
        <int>29</int>
        <member>
          <characterId>1741</characterId>
        </member>
      </entry>
      <entry>
        <int>14</int>
        <member>
          <characterId>548</characterId>
        </member>
      </entry>
      <entry>
        <int>68</int>
        <member>
          <characterId>627</characterId>
        </member>
      </entry>
      <entry>
        <int>47</int>
        <member>
          <characterId>1382</characterId>
        </member>
      </entry>
      <entry>
        <int>18</int>
        <member>
          <characterId>1809</characterId>
        </member>
      </entry>
      <entry>
        <int>3</int>
        <member>
          <characterId>799</characterId>
        </member>
      </entry>
      <entry>
        <int>98</int>
        <member>
          <characterId>325</characterId>
        </member>
      </entry>
      <entry>
        <int>12</int>
        <member>
          <characterId>56</characterId>
        </member>
      </entry>
      <entry>
        <int>27</int>
        <member>
          <characterId>1666</characterId>
        </member>
      </entry>
      <entry>
        <int>44</int>
        <member>
          <characterId>783</characterId>
        </member>
      </entry>
      <entry>
        <int>17</int>
        <member>
          <characterId>1333</characterId>
        </member>
      </entry>
      <entry>
        <int>2</int>
        <member>
          <characterId>393</characterId>
        </member>
      </entry>
      <entry>
        <int>13</int>
        <member>
          <characterId>978</characterId>
        </member>
      </entry>
      <entry>
        <int>28</int>
        <member>
          <characterId>2041</characterId>
        </member>
      </entry>
      <entry>
        <int>38</int>
        <member>
          <characterId>367</characterId>
        </member>
      </entry>
      <entry>
        <int>37</int>
        <member>
          <characterId>1652</characterId>
        </member>
      </entry>
      <entry>
        <int>8</int>
        <member>
          <characterId>2134</characterId>
        </member>
      </entry>
      <entry>
        <int>23</int>
        <member>
          <characterId>544</characterId>
        </member>
      </entry>
      <entry>
        <int>40</int>
        <member>
          <characterId>2098</characterId>
        </member>
      </entry>
      <entry>
        <int>35</int>
        <member>
          <characterId>106</characterId>
        </member>
      </entry>
      <entry>
        <int>7</int>
        <member>
          <characterId>1750</characterId>
        </member>
      </entry>
      <entry>
        <int>49</int>
        <member>
          <characterId>1690</characterId>
        </member>
      </entry>
      <entry>
        <int>22</int>
        <member>
          <characterId>519</characterId>
        </member>
      </entry>
      <entry>
        <int>9</int>
        <member>
          <characterId>9</characterId>
        </member>
      </entry>
      <entry>
        <int>21</int>
        <member>
          <characterId>329</characterId>
        </member>
      </entry>
      <entry>
        <int>33</int>
        <member>
          <characterId>55</characterId>
        </member>
      </entry>
      <entry>
        <int>6</int>
        <member>
          <characterId>1695</characterId>
        </member>
      </entry>
      <entry>
        <int>24</int>
        <member>
          <characterId>1630</characterId>
        </member>
      </entry>
      <entry>
        <int>42</int>
        <member>
          <characterId>1901</characterId>
        </member>
      </entry>
      <entry>
        <int>4</int>
        <member>
          <characterId>78</characterId>
        </member>
      </entry>
      <entry>
        <int>19</int>
        <member>
          <characterId>1423</characterId>
        </member>
      </entry>
      <entry>
        <int>36</int>
        <member>
          <characterId>943</characterId>
        </member>
      </entry>
      <entry>
        <int>26</int>
        <member>
          <characterId>1654</characterId>
        </member>
      </entry>
      <entry>
        <int>11</int>
        <member>
          <characterId>465</characterId>
        </member>
      </entry>
      <entry>
        <int>39</int>
        <member>
          <characterId>769</characterId>
        </member>
      </entry>
      <entry>
        <int>45</int>
        <member>
          <characterId>895</characterId>
        </member>
      </entry>
      <entry>
        <int>20</int>
        <member>
          <characterId>310</characterId>
        </member>
      </entry>
      <entry>
        <int>46</int>
        <member>
          <characterId>1193</characterId>
        </member>
      </entry>
      <entry>
        <int>25</int>
        <member>
          <characterId>1647</characterId>
        </member>
      </entry>
      <entry>
        <int>10</int>
        <member>
          <characterId>883</characterId>
        </member>
      </entry>
      <entry>
        <int>5</int>
        <member>
          <characterId>1754</characterId>
        </member>
	</entry>
	      <entry>
        <int>99</int>
        <member>
          <characterId>2362</characterId>
        </member>
      </entry>
    </sequenceMap>
  </members>
</category>
